setup.py
jump_ex_sar_forex_next3/__init__.py
jump_ex_sar_forex_next3/jump_ex_sar_forex_next3.py
jump_ex_sar_forex_next3.egg-info/PKG-INFO
jump_ex_sar_forex_next3.egg-info/SOURCES.txt
jump_ex_sar_forex_next3.egg-info/dependency_links.txt
jump_ex_sar_forex_next3.egg-info/not-zip-safe
jump_ex_sar_forex_next3.egg-info/top_level.txt